FoodSim/__init__.py
FoodSim/board.py
FoodSim/board_log.py
FoodSim/company.py
FoodSim/company_type.py
FoodSim/constants.py
FoodSim/events.py
FoodSim/func.py
FoodSim/house.py
FoodSim/id.py
FoodSim/person.py
FoodSim/store.py
matts_food_sim-1.1.dist-info/LICENSE
matts_food_sim-1.1.dist-info/METADATA
matts_food_sim-1.1.dist-info/WHEEL
matts_food_sim-1.1.dist-info/top_level.txt
matts_food_sim-1.1.dist-info/RECORD
